{
  "id": "779186bd-a0b5-40b5-8c9c-fe1665c87d18",
  "prevId": "753a3f72-a7e3-4ba2-a984-7abb6d241241",
  "version": "5",
  "dialect": "pg",
  "tables": {
    "balance": {
      "name": "balance",
      "schema": "",
      "columns": {
        "id": {
          "name": "id",
          "type": "serial",
          "primaryKey": false,
          "notNull": true
        },
        "user_id": {
          "name": "user_id",
          "type": "integer",
          "primaryKey": false,
          "notNull": false
        },
        "expense_id": {
          "name": "expense_id",
          "type": "integer",
          "primaryKey": false,
          "notNull": false
        },
        "group_id": {
          "name": "group_id",
          "type": "integer",
          "primaryKey": false,
          "notNull": false
        },
        "paid_share": {
          "name": "paid_share",
          "type": "integer",
          "primaryKey": false,
          "notNull": false
        },
        "owed_share": {
          "name": "owed_share",
          "type": "integer",
          "primaryKey": false,
          "notNull": false
        },
        "net_balance": {
          "name": "net_balance",
          "type": "integer",
          "primaryKey": false,
          "notNull": false
        }
      },
      "indexes": {},
      "foreignKeys": {
        "balance_user_id_user_id_fk": {
          "name": "balance_user_id_user_id_fk",
          "tableFrom": "balance",
          "tableTo": "user",
          "columnsFrom": [
            "user_id"
          ],
          "columnsTo": [
            "id"
          ],
          "onDelete": "no action",
          "onUpdate": "no action"
        },
        "balance_expense_id_expense_id_fk": {
          "name": "balance_expense_id_expense_id_fk",
          "tableFrom": "balance",
          "tableTo": "expense",
          "columnsFrom": [
            "expense_id"
          ],
          "columnsTo": [
            "id"
          ],
          "onDelete": "no action",
          "onUpdate": "no action"
        },
        "balance_group_id_group_id_fk": {
          "name": "balance_group_id_group_id_fk",
          "tableFrom": "balance",
          "tableTo": "group",
          "columnsFrom": [
            "group_id"
          ],
          "columnsTo": [
            "id"
          ],
          "onDelete": "no action",
          "onUpdate": "no action"
        }
      },
      "compositePrimaryKeys": {
        "balance_pk": {
          "name": "balance_pk",
          "columns": [
            "id"
          ]
        }
      },
      "uniqueConstraints": {}
    },
    "expense": {
      "name": "expense",
      "schema": "",
      "columns": {
        "id": {
          "name": "id",
          "type": "serial",
          "primaryKey": false,
          "notNull": true
        },
        "title": {
          "name": "title",
          "type": "text",
          "primaryKey": false,
          "notNull": true
        },
        "amount": {
          "name": "amount",
          "type": "numeric",
          "primaryKey": false,
          "notNull": true
        },
        "details": {
          "name": "details",
          "type": "text",
          "primaryKey": false,
          "notNull": false
        },
        "payer_id": {
          "name": "payer_id",
          "type": "integer",
          "primaryKey": false,
          "notNull": true
        },
        "group_id": {
          "name": "group_id",
          "type": "integer",
          "primaryKey": false,
          "notNull": true
        },
        "split_equally": {
          "name": "split_equally",
          "type": "boolean",
          "primaryKey": false,
          "notNull": false,
          "default": true
        },
        "created_at": {
          "name": "created_at",
          "type": "timestamp",
          "primaryKey": false,
          "notNull": false,
          "default": "now()"
        },
        "created_by": {
          "name": "created_by",
          "type": "integer",
          "primaryKey": false,
          "notNull": false
        },
        "updated_at": {
          "name": "updated_at",
          "type": "timestamp",
          "primaryKey": false,
          "notNull": false
        },
        "updated_by": {
          "name": "updated_by",
          "type": "integer",
          "primaryKey": false,
          "notNull": false
        },
        "deleted_at": {
          "name": "deleted_at",
          "type": "timestamp",
          "primaryKey": false,
          "notNull": false
        },
        "deleted_by": {
          "name": "deleted_by",
          "type": "integer",
          "primaryKey": false,
          "notNull": false
        },
        "is_deleted": {
          "name": "is_deleted",
          "type": "boolean",
          "primaryKey": false,
          "notNull": false,
          "default": false
        }
      },
      "indexes": {},
      "foreignKeys": {
        "expense_payer_id_user_id_fk": {
          "name": "expense_payer_id_user_id_fk",
          "tableFrom": "expense",
          "tableTo": "user",
          "columnsFrom": [
            "payer_id"
          ],
          "columnsTo": [
            "id"
          ],
          "onDelete": "no action",
          "onUpdate": "no action"
        },
        "expense_group_id_group_id_fk": {
          "name": "expense_group_id_group_id_fk",
          "tableFrom": "expense",
          "tableTo": "group",
          "columnsFrom": [
            "group_id"
          ],
          "columnsTo": [
            "id"
          ],
          "onDelete": "no action",
          "onUpdate": "no action"
        },
        "expense_created_by_user_id_fk": {
          "name": "expense_created_by_user_id_fk",
          "tableFrom": "expense",
          "tableTo": "user",
          "columnsFrom": [
            "created_by"
          ],
          "columnsTo": [
            "id"
          ],
          "onDelete": "no action",
          "onUpdate": "no action"
        },
        "expense_updated_by_user_id_fk": {
          "name": "expense_updated_by_user_id_fk",
          "tableFrom": "expense",
          "tableTo": "user",
          "columnsFrom": [
            "updated_by"
          ],
          "columnsTo": [
            "id"
          ],
          "onDelete": "no action",
          "onUpdate": "no action"
        },
        "expense_deleted_by_user_id_fk": {
          "name": "expense_deleted_by_user_id_fk",
          "tableFrom": "expense",
          "tableTo": "user",
          "columnsFrom": [
            "deleted_by"
          ],
          "columnsTo": [
            "id"
          ],
          "onDelete": "no action",
          "onUpdate": "no action"
        }
      },
      "compositePrimaryKeys": {
        "expense_pk": {
          "name": "expense_pk",
          "columns": [
            "id"
          ]
        }
      },
      "uniqueConstraints": {}
    },
    "friend": {
      "name": "friend",
      "schema": "",
      "columns": {
        "id": {
          "name": "id",
          "type": "serial",
          "primaryKey": false,
          "notNull": true
        },
        "friend_1": {
          "name": "friend_1",
          "type": "integer",
          "primaryKey": false,
          "notNull": false
        },
        "friend_2": {
          "name": "friend_2",
          "type": "integer",
          "primaryKey": false,
          "notNull": false
        }
      },
      "indexes": {},
      "foreignKeys": {
        "friend_friend_1_user_id_fk": {
          "name": "friend_friend_1_user_id_fk",
          "tableFrom": "friend",
          "tableTo": "user",
          "columnsFrom": [
            "friend_1"
          ],
          "columnsTo": [
            "id"
          ],
          "onDelete": "no action",
          "onUpdate": "no action"
        },
        "friend_friend_2_user_id_fk": {
          "name": "friend_friend_2_user_id_fk",
          "tableFrom": "friend",
          "tableTo": "user",
          "columnsFrom": [
            "friend_2"
          ],
          "columnsTo": [
            "id"
          ],
          "onDelete": "no action",
          "onUpdate": "no action"
        }
      },
      "compositePrimaryKeys": {},
      "uniqueConstraints": {
        "friend_uk": {
          "name": "friend_uk",
          "nullsNotDistinct": false,
          "columns": [
            "friend_1",
            "friend_2"
          ]
        }
      }
    },
    "group": {
      "name": "group",
      "schema": "",
      "columns": {
        "id": {
          "name": "id",
          "type": "serial",
          "primaryKey": true,
          "notNull": true
        },
        "title": {
          "name": "title",
          "type": "text",
          "primaryKey": false,
          "notNull": false
        },
        "type": {
          "name": "type",
          "type": "text",
          "primaryKey": false,
          "notNull": false
        },
        "simplify_debt": {
          "name": "simplify_debt",
          "type": "boolean",
          "primaryKey": false,
          "notNull": false,
          "default": false
        },
        "is_deleted": {
          "name": "is_deleted",
          "type": "boolean",
          "primaryKey": false,
          "notNull": false,
          "default": false
        },
        "created_at": {
          "name": "created_at",
          "type": "timestamp",
          "primaryKey": false,
          "notNull": false,
          "default": "now()"
        },
        "updated_at": {
          "name": "updated_at",
          "type": "timestamp",
          "primaryKey": false,
          "notNull": false
        }
      },
      "indexes": {},
      "foreignKeys": {},
      "compositePrimaryKeys": {},
      "uniqueConstraints": {}
    },
    "group_members": {
      "name": "group_members",
      "schema": "",
      "columns": {
        "group_id": {
          "name": "group_id",
          "type": "integer",
          "primaryKey": false,
          "notNull": false
        },
        "user_id": {
          "name": "user_id",
          "type": "integer",
          "primaryKey": false,
          "notNull": false
        }
      },
      "indexes": {},
      "foreignKeys": {
        "group_members_group_id_group_id_fk": {
          "name": "group_members_group_id_group_id_fk",
          "tableFrom": "group_members",
          "tableTo": "group",
          "columnsFrom": [
            "group_id"
          ],
          "columnsTo": [
            "id"
          ],
          "onDelete": "no action",
          "onUpdate": "no action"
        },
        "group_members_user_id_user_id_fk": {
          "name": "group_members_user_id_user_id_fk",
          "tableFrom": "group_members",
          "tableTo": "user",
          "columnsFrom": [
            "user_id"
          ],
          "columnsTo": [
            "id"
          ],
          "onDelete": "no action",
          "onUpdate": "no action"
        }
      },
      "compositePrimaryKeys": {
        "group_members_pk": {
          "name": "group_members_pk",
          "columns": [
            "user_id",
            "group_id"
          ]
        }
      },
      "uniqueConstraints": {}
    },
    "user": {
      "name": "user",
      "schema": "",
      "columns": {
        "id": {
          "name": "id",
          "type": "serial",
          "primaryKey": true,
          "notNull": true
        },
        "first_name": {
          "name": "first_name",
          "type": "text",
          "primaryKey": false,
          "notNull": false
        },
        "last_name": {
          "name": "last_name",
          "type": "text",
          "primaryKey": false,
          "notNull": false
        },
        "email": {
          "name": "email",
          "type": "text",
          "primaryKey": false,
          "notNull": false
        },
        "created_at": {
          "name": "created_at",
          "type": "timestamp",
          "primaryKey": false,
          "notNull": false,
          "default": "now()"
        },
        "updated_at": {
          "name": "updated_at",
          "type": "timestamp",
          "primaryKey": false,
          "notNull": false,
          "default": "now()"
        },
        "registration_status": {
          "name": "registration_status",
          "type": "boolean",
          "primaryKey": false,
          "notNull": false,
          "default": false
        },
        "custom_picture": {
          "name": "custom_picture",
          "type": "boolean",
          "primaryKey": false,
          "notNull": false,
          "default": false
        },
        "default_currency": {
          "name": "default_currency",
          "type": "text",
          "primaryKey": false,
          "notNull": false
        },
        "locale": {
          "name": "locale",
          "type": "text",
          "primaryKey": false,
          "notNull": false
        }
      },
      "indexes": {},
      "foreignKeys": {},
      "compositePrimaryKeys": {},
      "uniqueConstraints": {}
    }
  },
  "enums": {},
  "schemas": {},
  "_meta": {
    "columns": {},
    "schemas": {},
    "tables": {}
  }
}